[
  {
    "case_count": "6",
    "disease_id": 7,
    "state_id": 1
  },
  {
    "case_count": "202",
    "disease_id": 7,
    "state_id": 2
  },
  {
    "case_count": "5",
    "disease_id": 7,
    "state_id": 3
  },
  {
    "case_count": "3",
    "disease_id": 7,
    "state_id": 4
  },
  {
    "case_count": "26",
    "disease_id": 7,
    "state_id": 5
  },
  {
    "case_count": "13",
    "disease_id": 7,
    "state_id": 6
  },
  {
    "case_count": "2",
    "disease_id": 7,
    "state_id": 7
  },
  {
    "case_count": "21",
    "disease_id": 7,
    "state_id": 8
  },
  {
    "case_count": "29",
    "disease_id": 7,
    "state_id": 9
  },
  {
    "case_count": "8",
    "disease_id": 7,
    "state_id": 10
  },
  {
    "case_count": "No Cases Reported",
    "disease_id": 7,
    "state_id": 11
  },
  {
    "case_count": "186",
    "disease_id": 7,
    "state_id": 12
  },
  {
    "case_count": "1",
    "disease_id": 7,
    "state_id": 13
  },
  {
    "case_count": "83",
    "disease_id": 7,
    "state_id": 14
  },
  {
    "case_count": "5",
    "disease_id": 7,
    "state_id": 15
  },
  {
    "case_count": "10",
    "disease_id": 7,
    "state_id": 16
  },
  {
    "case_count": "1",
    "disease_id": 7,
    "state_id": 17
  },
  {
    "case_count": "5",
    "disease_id": 7,
    "state_id": 18
  },
  {
    "case_count": "2",
    "disease_id": 7,
    "state_id": 19
  },
  {
    "case_count": "4",
    "disease_id": 7,
    "state_id": 20
  },
  {
    "case_count": "20",
    "disease_id": 7,
    "state_id": 21
  },
  {
    "case_count": "17",
    "disease_id": 7,
    "state_id": 22
  },
  {
    "case_count": "11",
    "disease_id": 7,
    "state_id": 23
  },
  {
    "case_count": "4",
    "disease_id": 7,
    "state_id": 24
  },
  {
    "case_count": "2",
    "disease_id": 7,
    "state_id": 25
  },
  {
    "case_count": "16",
    "disease_id": 7,
    "state_id": 26
  },
  {
    "case_count": "2",
    "disease_id": 7,
    "state_id": 27
  },
  {
    "case_count": "1",
    "disease_id": 7,
    "state_id": 28
  },
  {
    "case_count": "1",
    "disease_id": 7,
    "state_id": 29
  },
  {
    "case_count": "1",
    "disease_id": 7,
    "state_id": 30
  },
  {
    "case_count": "19",
    "disease_id": 7,
    "state_id": 31
  },
  {
    "case_count": "2",
    "disease_id": 7,
    "state_id": 32
  },
  {
    "case_count": "40",
    "disease_id": 7,
    "state_id": 33
  },
  {
    "case_count": "4",
    "disease_id": 7,
    "state_id": 34
  },
  {
    "case_count": "No Cases Reported",
    "disease_id": 7,
    "state_id": 35
  },
  {
    "case_count": "18",
    "disease_id": 7,
    "state_id": 36
  },
  {
    "case_count": "6",
    "disease_id": 7,
    "state_id": 37
  },
  {
    "case_count": "12",
    "disease_id": 7,
    "state_id": 38
  },
  {
    "case_count": "98",
    "disease_id": 7,
    "state_id": 39
  },
  {
    "case_count": "No Cases Reported",
    "disease_id": 7,
    "state_id": 40
  },
  {
    "case_count": "2",
    "disease_id": 7,
    "state_id": 41
  },
  {
    "case_count": "3",
    "disease_id": 7,
    "state_id": 42
  },
  {
    "case_count": "No Cases Reported",
    "disease_id": 7,
    "state_id": 43
  },
  {
    "case_count": "9",
    "disease_id": 7,
    "state_id": 44
  },
  {
    "case_count": "48",
    "disease_id": 7,
    "state_id": 45
  },
  {
    "case_count": "3",
    "disease_id": 7,
    "state_id": 46
  },
  {
    "case_count": "12",
    "disease_id": 7,
    "state_id": 47
  },
  {
    "case_count": "135",
    "disease_id": 7,
    "state_id": 48
  },
  {
    "case_count": "27",
    "disease_id": 7,
    "state_id": 49
  },
  {
    "case_count": "1",
    "disease_id": 7,
    "state_id": 50
  },
  {
    "case_count": "6",
    "disease_id": 7,
    "state_id": 51
  },
  {
    "case_count": "No Cases Reported",
    "disease_id": 7,
    "state_id": 52
  }
]